aiokadiapi/__init__.py
aiokadiapi/aio/__init__.py
aiokadiapi/aio/get_info.py
aiokadiapi/mp/__init__.py
aiokadiapi/mp/runner.py
aiokadiapi/mp/static.py
aiokadiapi-1.3.0.dist-info/METADATA
aiokadiapi-1.3.0.dist-info/WHEEL
aiokadiapi-1.3.0.dist-info/RECORD
